graviton/__init__.py
graviton-0.0.dist-info/LICENSE
graviton-0.0.dist-info/METADATA
graviton-0.0.dist-info/WHEEL
graviton-0.0.dist-info/top_level.txt
graviton-0.0.dist-info/RECORD
