Metadata-Version: 2.1
Name: graviton
Version: 0.0
Summary: The Graviton package
Home-page: https://github.com/facebookincubator/graviton
Author: Adam Obeng
Author-email: adamobeng@fb.com
License: UNKNOWN
Platform: UNKNOWN
Classifier: Programming Language :: Python :: 3
Classifier: License :: OSI Approved :: BSD License
Classifier: Operating System :: OS Independent
